pytagspace/__init__.py
pytagspace/tag_space.py
pytagspace-1.0.1.dist-info/LICENSE
pytagspace-1.0.1.dist-info/METADATA
pytagspace-1.0.1.dist-info/WHEEL
pytagspace-1.0.1.dist-info/top_level.txt
pytagspace-1.0.1.dist-info/RECORD
