Metadata-Version: 2.1
Name: pytagspace
Version: 1.0.1
Summary: A utility package that marks objects and finds them with tags.
Home-page: https://github.com/DecAngel/pytagspace
Author: Xiang Zhang
Author-email: xzhang1048576@gmail.com
License: UNKNOWN
Platform: UNKNOWN
Classifier: Programming Language :: Python :: 3
Classifier: License :: OSI Approved :: GNU General Public License v3 or later (GPLv3+)
Classifier: Operating System :: OS Independent
Requires-Python: >=3.6
